watchdogman/__init__.py
watchdogman/config.py
watchdogman/console.py
watchdogman/event.py
watchdogman/logger.py
watchdogman-0.0.1.dist-info/LICENSE
watchdogman-0.0.1.dist-info/METADATA
watchdogman-0.0.1.dist-info/WHEEL
watchdogman-0.0.1.dist-info/entry_points.txt
watchdogman-0.0.1.dist-info/top_level.txt
watchdogman-0.0.1.dist-info/RECORD
