Metadata-Version: 2.1
Name: watchdogman
Version: 0.0.1
Summary: A basic python-only file watcher with events
Author-email: Seth Jensen <sjensen85@gmail.com>
License: Apache License
Project-URL: Homepage, https://github.com/sjensen85/watchdogman
Project-URL: Bug Tracker, https://github.com/sjensen85/watchdogman/issues
Classifier: Programming Language :: Python :: 3
Classifier: License :: OSI Approved :: Apache Software License
Classifier: Operating System :: OS Independent
Requires-Python: >=3.7
License-File: LICENSE
Requires-Dist: watchdog
